branchify/__init__.py
branchify/cli.py
branchify/generator.py
branchify-1.0.3.dist-info/LICENSE
branchify-1.0.3.dist-info/METADATA
branchify-1.0.3.dist-info/WHEEL
branchify-1.0.3.dist-info/entry_points.txt
branchify-1.0.3.dist-info/top_level.txt
branchify-1.0.3.dist-info/RECORD
