Metadata-Version: 2.2
Name: branchify
Version: 1.0.3
Summary: Generate an ASCII folder structure of a directory
Home-page: https://github.com/VanshajR/branchify
Author: Vanshaj Raghuvanshi
Author-email: vanshajraghuvanshi@gmail.com
Classifier: Programming Language :: Python :: 3
Classifier: License :: OSI Approved :: BSD License
Classifier: Operating System :: OS Independent
Requires-Python: >=3.8
License-File: LICENSE
Dynamic: author
Dynamic: author-email
Dynamic: classifier
Dynamic: description
Dynamic: description-content-type
Dynamic: home-page
Dynamic: requires-python
Dynamic: summary
